{
  "date": "Wednesday 15 April 2026",
  "macro": {
    "badge": "📈 Inflationary Pressures, Geopolitical Tensions",
    "intro": "The macroeconomic landscape is characterized by <strong>rising inflation</strong> with CPI YoY at 330.29, up from 327.46. The <strong>10Y TIPS Real Yield</strong> has slightly decreased to 1.92%. The <strong>Fed Funds Rate</strong> remains stable at 3.64%. No major economic events are scheduled today, allowing markets to focus on geopolitical developments and earnings reports."
  },
  "snapshot": [
    {
      "name": "Gold (XAU/USD)",
      "value": "1985.50",
      "change": "±0.45% today",
      "dir": "up",
      "note": "Safe-haven demand amid geopolitical tensions"
    },
    {
      "name": "WTI Crude Oil",
      "value": "72.30",
      "change": "±-1.20% today",
      "dir": "down",
      "note": "Pressure from potential US-Iran talks"
    },
    {
      "name": "S&P 500",
      "value": "4480.25",
      "change": "±0.75% today",
      "dir": "up",
      "note": "Rally on earnings optimism"
    },
    {
      "name": "EUR/USD",
      "value": "1.1050",
      "change": "±0.0025 today",
      "dir": "up",
      "note": "Key resistance at 1.1100"
    },
    {
      "name": "VIX",
      "value": "18.50",
      "change": "±-0.50 today",
      "dir": "down",
      "note": "Risk-on sentiment as markets rally"
    }
  ],
  "setups": [
    {
      "rank": 1,
      "dir": "LONG",
      "type": "Commodity",
      "symbol": "XAU/USD",
      "name": "Gold Long Setup",
      "conviction": "High",
      "conviction_pct": 85,
      "rationale": "Gold is gaining as a safe-haven asset amid geopolitical tensions, with a current price of 1985.50. The CPI YoY inflation at 330.29 supports the inflation hedge narrative. No major economic events today to disrupt this trend.",
      "entry": "1980.00",
      "entry_note": "Buy on slight pullback",
      "target": "2020.00",
      "target_note": "Resistance at psychological level",
      "stop": "1960.00",
      "stop_note": "Support from recent lows",
      "metrics": [
        {
          "label": "CPI Inflation",
          "text": "High inflation supports gold as an inflation hedge"
        },
        {
          "label": "Geopolitical Tensions",
          "text": "Increased demand for safe-haven assets"
        },
        {
          "label": "Economic event",
          "text": "No events today, focus on geopolitical news"
        },
        {
          "label": "Technical Level",
          "text": "Resistance at 2020.00"
        }
      ],
      "concerns": [
        {
          "label": "Primary risk",
          "text": "Resolution in US-Iran talks could reduce safe-haven demand"
        },
        {
          "label": "Secondary risk",
          "text": "Unexpected Fed policy changes"
        }
      ],
      "hedge": "Consider shorting EUR/USD at 1.1100 if gold weakens."
    },
    {
      "rank": 2,
      "dir": "SHORT",
      "type": "Index",
      "symbol": "S&P 500",
      "name": "S&P 500 Short Setup",
      "conviction": "Moderate–High",
      "conviction_pct": 75,
      "rationale": "Despite the rally, the S&P 500 at 4480.25 may face resistance due to geopolitical uncertainties. The 10Y-2Y yield spread narrowing to 0.5% suggests potential economic slowdown concerns.",
      "entry": "4500.00",
      "entry_note": "Short at resistance level",
      "target": "4400.00",
      "target_note": "Support from recent lows",
      "stop": "4525.00",
      "stop_note": "Above recent highs",
      "metrics": [
        {
          "label": "Yield Spread",
          "text": "Narrowing spread indicates economic caution"
        },
        {
          "label": "Geopolitical Tensions",
          "text": "Potential for market volatility"
        },
        {
          "label": "Economic event",
          "text": "No events today, focus on geopolitical news"
        },
        {
          "label": "Technical Level",
          "text": "Resistance at 4500.00"
        }
      ],
      "concerns": [
        {
          "label": "Primary risk",
          "text": "Continued rally on earnings optimism"
        },
        {
          "label": "Secondary risk",
          "text": "Improvement in geopolitical situation"
        }
      ],
      "hedge": "Consider long VIX at 18.00 if volatility increases."
    },
    {
      "rank": 3,
      "dir": "LONG",
      "type": "FX Pair",
      "symbol": "EUR/USD",
      "name": "EUR/USD Long Setup",
      "conviction": "Moderate",
      "conviction_pct": 65,
      "rationale": "EUR/USD is trading at 1.1050, with potential to test resistance at 1.1100. The stable Fed Funds Rate at 3.64% supports a weaker USD narrative.",
      "entry": "1.1030",
      "entry_note": "Buy on minor dip",
      "target": "1.1100",
      "target_note": "Resistance level",
      "stop": "1.1000",
      "stop_note": "Support from recent lows",
      "metrics": [
        {
          "label": "Fed Funds Rate",
          "text": "Stable rate supports weaker USD"
        },
        {
          "label": "Technical Level",
          "text": "Resistance at 1.1100"
        },
        {
          "label": "Economic event",
          "text": "No events today, focus on technicals"
        },
        {
          "label": "Geopolitical Tensions",
          "text": "Potential impact on USD strength"
        }
      ],
      "concerns": [
        {
          "label": "Primary risk",
          "text": "USD strength if geopolitical tensions ease"
        },
        {
          "label": "Secondary risk",
          "text": "Unexpected ECB policy changes"
        }
      ],
      "hedge": "Consider shorting Gold at 2020.00 if EUR/USD weakens."
    }
  ],
  "contrarian": {
    "symbol": "WTI Crude Oil",
    "dir": "LONG",
    "entry": "72.00",
    "stop": "70.00",
    "target": "76.00",
    "rr": "1:2.0",
    "body": "WTI Crude Oil is currently at 72.30, pressured by potential US-Iran talks. However, geopolitical tensions remain high, suggesting a potential rebound. The narrowing 10Y-2Y yield spread at 0.5% indicates economic caution, which could support oil prices.",
    "warning": "A breakthrough in US-Iran talks could lead to a significant drop in oil prices. <strong>Monitor geopolitical developments closely</strong>."
  },
  "avoid": [
    {
      "symbol": "📉 Nasdaq",
      "reason": "Extended rally with 9 consecutive sessions in green, potential overbought risk."
    },
    {
      "symbol": "📉 UK Stocks",
      "reason": "IMF growth downgrade due to Iran war impacts, increasing inflation concerns."
    },
    {
      "symbol": "📉 Middle East ETFs",
      "reason": "IMF slashes growth forecast for the region amid ongoing conflicts."
    },
    {
      "symbol": "📉 Airlines",
      "reason": "Potential disruptions from geopolitical tensions and rising fuel costs."
    },
    {
      "symbol": "📉 Fertilizer Stocks",
      "reason": "Supply concerns due to Iran war, impacting global agricultural markets."
    },
    {
      "symbol": "📉 Lululemon",
      "reason": "Potential legal issues over 'forever chemicals' in activewear."
    }
  ]
}